ntfpy/__init__.py
ntfpy/raw_send.py
ntfpy/raw_subscribe.py
ntfpy/types/__init__.py
ntfpy/types/client.py
ntfpy/types/message.py
ntfpy/types/push_message.py
ntfpy/types/server.py
ntfpy/types/user.py
ntfpy/types/actions/__init__.py
ntfpy/types/actions/action.py
ntfpy/types/actions/android_broadcast.py
ntfpy/types/actions/http.py
ntfpy/types/actions/view.py
ntfpy/types/attachments/__init__.py
ntfpy/types/attachments/url.py
ntfpy-0.0.12.dist-info/LICENSE.md
ntfpy-0.0.12.dist-info/METADATA
ntfpy-0.0.12.dist-info/WHEEL
ntfpy-0.0.12.dist-info/top_level.txt
ntfpy-0.0.12.dist-info/RECORD
