Metadata-Version: 2.1
Name: ntfpy
Version: 0.0.12
Summary: Python ntfy.sh API Wrapper
Home-page: https://github.com/nevalicjus/ntfpy
Author: Nevalicjus
Author-email: nevalicjus@gmail.com
Project-URL: Author, https://nevalicj.us
Project-URL: Bug Tracker, https://github.com/nevalicjus/ntfpy/issues
Classifier: Programming Language :: Python :: 3
Classifier: License :: OSI Approved :: MIT License
Classifier: Operating System :: OS Independent
Requires-Python: >=3.6
License-File: LICENSE.md
Requires-Dist: requests
